gifton/__init__.py
gifton-1.0.3.dist-info/METADATA
gifton-1.0.3.dist-info/WHEEL
gifton-1.0.3.dist-info/top_level.txt
gifton-1.0.3.dist-info/RECORD
