Metadata-Version: 2.4
Name: gifton
Version: 1.0.3
Summary: This is a library with encryption. I created it to surprise my friend for his birthday. Please don't delete it.
Author: eropens
Author-email: eropn313@gmail.com
Classifier: Programming Language :: Python :: 3
Classifier: Operating System :: OS Independent
Requires-Python: >=3.6
Dynamic: author
Dynamic: author-email
Dynamic: classifier
Dynamic: requires-python
Dynamic: summary
